weather_reporter/cli.py
weather_reporter/utils.py
weather_reportee-0.0.1.dist-info/LICENSE.txt
weather_reportee-0.0.1.dist-info/METADATA
weather_reportee-0.0.1.dist-info/WHEEL
weather_reportee-0.0.1.dist-info/entry_points.txt
weather_reportee-0.0.1.dist-info/top_level.txt
weather_reportee-0.0.1.dist-info/RECORD
