Metadata-Version: 2.1
Name: weather-reportee
Version: 0.0.1
Summary: A Python package to get weather reports for any location.
Home-page: https://github.com/nikhilkumarsingh/weather-reporter
Author: cave_man
Author-email: amaryesh123456@gmail.com
License: MIT
Platform: UNKNOWN
Classifier: License :: OSI Approved :: MIT License
Classifier: Programming Language :: Python :: 3
Classifier: Programming Language :: Python :: 3.7
Requires-Dist: requests
